AUTHORS.rst
CONTRIBUTING.rst
HISTORY.rst
LICENSE
MANIFEST.in
README.rst
setup.cfg
setup.py
docs/Makefile
docs/authors.rst
docs/conf.py
docs/contributing.rst
docs/history.rst
docs/index.rst
docs/installation.rst
docs/make.bat
docs/readme.rst
docs/usage.rst
tests/__init__.py
tests/test_ticker_1.txt
tests/test_ticker_2.txt
tests/test_tiingo_prices.py
tiingo_prices/__init__.py
tiingo_prices/tiingo_prices.py
tiingo_prices.egg-info/PKG-INFO
tiingo_prices.egg-info/SOURCES.txt
tiingo_prices.egg-info/dependency_links.txt
tiingo_prices.egg-info/entry_points.txt
tiingo_prices.egg-info/not-zip-safe
tiingo_prices.egg-info/requires.txt
tiingo_prices.egg-info/top_level.txt