Metadata-Version: 2.1
Name: tiingo-prices
Version: 0.3.1
Summary: A CLI tool to get close of day price and annual dividends
Home-page: https://github.com/robren/tiingo_prices
Author: Robert Rennison
Author-email: rob@robren.net
License: MIT license
Keywords: tiingo_prices tiingo finance
Platform: UNKNOWN
Classifier: Development Status :: 3 - Alpha
Classifier: Intended Audience :: Developers
Classifier: License :: OSI Approved :: MIT License
Classifier: Natural Language :: English
Classifier: Programming Language :: Python :: 3
Classifier: Programming Language :: Python :: 3.7
Classifier: Programming Language :: Python :: 3.8
